{
  "timestamp": "2023-03-02T06:18:27.0000000+00:00",
  "category": {
    "oldValue": null,
    "newValue": [
      "Android",
      "Desktop",
      "GCC High",
      "General Availability",
      "iOS",
      "Launched",
      "Mobile",
      "Outlook",
      "Web"
    ]
  },
  "title": {
    "oldValue": null,
    "newValue": "Outlook: Suggested replies expansion to GCC high"
  },
  "description": {
    "oldValue": null,
    "newValue": "Outlook on the web, Outlook mobile, and Outlook for Windows are adding suggested replies for GCC high customers. <br>GA date: November CY2022"
  }
}
