{
  "timestamp": "2025-04-05T02:27:18.5316356+00:00",
  "guid": "485767",
  "link": "https://www.microsoft.com/microsoft-365/roadmap?id=485767",
  "category": [
    "DoD",
    "GCC",
    "GCC High",
    "General Availability",
    "In development",
    "Microsoft Purview compliance portal",
    "Web"
  ],
  "title": "Microsoft Purview compliance portal: Data Security Posture Management for AI - Data Assessments",
  "description": "Data assessments in Microsoft Purview Data Security Posture Management for AI provides a way for admins to drive data security outcomes by viewing default assessments, reviewing the data sensitivity and user accesses on locations, and performing remediation actions to mitigate risk.",
  "pubDate": "Sat, 05 Apr 2025 00:00:03 Z",
  "updated": "2025-04-05T00:00:03Z",
  "publicDisclosureAvailabilityDate": "May CY2025",
  "publicPreviewDate": null
}
