{
  "timestamp": "2023-03-02T06:18:27.0000000+00:00",
  "guid": "108865",
  "link": "https://www.microsoft.com/microsoft-365/roadmap?featureid=108865",
  "category": [
    "General Availability",
    "Launched",
    "Microsoft Viva",
    "Planner",
    "Web",
    "Worldwide (Standard Multi-Tenant)"
  ],
  "title": "Microsoft Viva: Microsoft Planner Integration",
  "description": "Connect Viva Goals projects and key results to Microsoft Planner.  <br>GA date: January CY2023",
  "pubDate": "Fri, 09 Dec 2022 23:12:50 -0800",
  "updated": "2023-02-10T08:14:01+00:00"
}
