{
  "timestamp": "2023-04-14T02:24:46.0000000+00:00",
  "guid": "89100",
  "link": "https://www.microsoft.com/microsoft-365/roadmap?featureid=89100",
  "category": [
    "General Availability",
    "Launched",
    "Microsoft Teams",
    "Web",
    "Worldwide (Standard Multi-Tenant)"
  ],
  "title": "Microsoft Teams: Microsoft Teams chat embedded within Dynamics 365",
  "description": "Microsoft Teams chat can be accessed directly from Dynamics 365 allowing users to continue existing chats or create new individual or group chats.",
  "pubDate": "Fri, 06 May 2022 22:06:45 -0700",
  "updated": "2023-04-14T06:09:10+00:00",
  "publicDisclosureAvailabilityDate": "September CY2022",
  "publicPreviewDate": null
}
