{
  "timestamp": "2023-03-02T06:18:27.0000000+00:00",
  "guid": "102403",
  "link": "https://www.microsoft.com/microsoft-365/roadmap?featureid=102403",
  "category": [
    "GCC",
    "General Availability",
    "Launched",
    "Microsoft 365 Admin Center",
    "Web",
    "Worldwide (Standard Multi-Tenant)"
  ],
  "title": "Microsoft 365 admin center: Configure your Zero Trust security model with a new guide",
  "description": "We’ll add a guide to the Advanced deployment guides page that will help you implement the Zero Trust security strategy. This strategy recommends that you verify explicitly, use least privilege access, and assume breach. You’ll use Zero Trust to help secure identities, endpoints, data, apps, infrastructure, and networks.<br>GA date: November CY2022",
  "pubDate": "Wed, 02 Nov 2022 23:14:57 -0700",
  "updated": "2022-11-11T08:07:07+00:00"
}
