{
  "timestamp": "2023-03-09T21:11:53.0000000+00:00",
  "description": {
    "oldValue": "A new update to Teams admin center will extend the ability of an Admin to configure the call management capabilities for end-users. The existing call management capabilities of call delegation and group call pickup are being extended to also include the ability to manage an end-user's call forwarding and simultaneous ringing settings as well.  <br>GA date: April CY2022",
    "newValue": "A new update to Teams admin center will extend the ability of an Admin to configure the call management capabilities for end-users. The existing call management capabilities of call delegation and group call pickup are being extended to also include the ability to manage an end-user's call forwarding and simultaneous ringing settings as well."
  },
  "publicDisclosureAvailabilityDate": {
    "oldValue": null,
    "newValue": "April CY2022"
  }
}
