{
  "timestamp": "2023-03-02T06:18:27.0000000+00:00",
  "category": {
    "oldValue": null,
    "newValue": [
      "Desktop",
      "General Availability",
      "Microsoft Teams",
      "Rolling out",
      "Web",
      "Worldwide (Standard Multi-Tenant)"
    ]
  },
  "title": {
    "oldValue": null,
    "newValue": "Microsoft Teams: On-demand Virtual Appointments"
  },
  "description": {
    "oldValue": null,
    "newValue": "Enable on-demand B2C appointments to allow customers to meet with staff in businesses or departments right away without requiring them to schedule it in advance. <br>GA date: December CY2022"
  }
}
