{
  "timestamp": "2023-03-02T06:18:27.0000000+00:00",
  "category": {
    "oldValue": null,
    "newValue": [
      "DoD",
      "GCC High",
      "General Availability",
      "Launched",
      "Microsoft Purview compliance portal",
      "Web"
    ]
  },
  "title": {
    "oldValue": null,
    "newValue": "Microsoft Purview compliance portal:  Data Lifecycle Management - Adaptive retention policies"
  },
  "description": {
    "oldValue": null,
    "newValue": "This update allows admins to create retention policies scoped to geography, department, or other user or site attribute. For example, admins can create a policy specifically for users in the UK's human resources team by leveraging the adaptive policy scope. <br>More info: https://docs.microsoft.com/en-us/microsoft-365/compliance/get-started-with-data-lifecycle-management?view=o365-worldwide<br>GA date: October CY2022"
  }
}
