{
  "timestamp": "2023-03-09T21:11:53.0000000+00:00",
  "description": {
    "oldValue": "An administrator will have the ability to resize Cloud PCs of users who are licensed via Group Based Licensing. Administrators will be able to resize multiple Cloud PCs at once. This will work for upgrades as well as downgrades.<br>GA date: June CY2023",
    "newValue": "An administrator will have the ability to resize Cloud PCs of users who are licensed via Group Based Licensing. Administrators will be able to resize multiple Cloud PCs at once. This will work for upgrades as well as downgrades."
  },
  "publicDisclosureAvailabilityDate": {
    "oldValue": null,
    "newValue": "June CY2023"
  }
}
