{
  "timestamp": "2024-11-13T02:23:49.9826350+00:00",
  "guid": "418131",
  "link": "https://www.microsoft.com/microsoft-365/roadmap?featureid=418131",
  "category": [
    "DoD",
    "GCC",
    "GCC High",
    "General Availability",
    "In development",
    "Microsoft Purview compliance portal",
    "Web"
  ],
  "title": "Microsoft Purview compliance portal: Data Loss Prevention - Message/Attachment contains EXO predicates",
  "description": "Introducing two new DLP Exchange predicates: \"Message contains\" and \"Attachment contains\" with a focus on DLP evaluation on only specific email components like email body or attachments. Unlike the broader \"Content contains\" predicate that evaluated entire email envelope, these enable targeted DLP evaluation on specific email components.",
  "pubDate": "Fri, 27 Sep 2024 22:45:32 Z",
  "updated": "2024-11-13T00:15:18Z",
  "publicDisclosureAvailabilityDate": "November CY2024",
  "publicPreviewDate": null
}
