{
  "timestamp": "2023-08-26T02:11:15.0000000+00:00",
  "category": {
    "oldValue": null,
    "newValue": [
      "General Availability",
      "In development",
      "Microsoft Viva",
      "Web",
      "Worldwide (Standard Multi-Tenant)"
    ]
  },
  "title": {
    "oldValue": null,
    "newValue": "Microsoft Viva: Viva Glint - Improved error messaging"
  },
  "description": {
    "oldValue": null,
    "newValue": "Improved error messaging during people import\nprocess."
  },
  "publicDisclosureAvailabilityDate": {
    "oldValue": null,
    "newValue": "December CY2023"
  }
}
