{
  "timestamp": "2023-03-09T21:11:53.0000000+00:00",
  "description": {
    "oldValue": ",Now eDiscovery admins can understand the progress of Collections, statistics on what content contributed to changes between estimated items with hits and actual collected items, as well as commit the collection directly from the estimate without navigating through the entire collection wizard. <br>GA date: February CY2023<br>Preview date: November CY2022",
    "newValue": ",Now eDiscovery admins can understand the progress of Collections, statistics on what content contributed to changes between estimated items with hits and actual collected items, as well as commit the collection directly from the estimate without navigating through the entire collection wizard."
  },
  "publicDisclosureAvailabilityDate": {
    "oldValue": null,
    "newValue": "February CY2023"
  },
  "publicPreviewDate": {
    "oldValue": null,
    "newValue": "November CY2022"
  }
}
