{
  "guid": "119153",
  "link": "https://www.microsoft.com/microsoft-365/roadmap?featureid=119153",
  "category": [
    "Android",
    "Desktop",
    "DoD",
    "GCC",
    "GCC High",
    "General Availability",
    "In development",
    "iOS",
    "Mac",
    "Microsoft Teams",
    "Targeted Release (Entire Organization)",
    "Targeted Release (Select People)",
    "Worldwide (Standard Multi-Tenant)"
  ],
  "title": "Microsoft Teams: Hide attendee names in Webinars (Premium)",
  "description": "Organizers can hide the names of attendees from\nother attendees during a webinar, and only organizers and presenters are able\nto see the names of attendees.",
  "pubDate": "Mon, 15 May 2023 23:10:30 -0700",
  "updated": "2023-10-24T23:06:35-07:00",
  "publicDisclosureAvailabilityDate": "November CY2023",
  "publicPreviewDate": null
}
