{
  "guid": "141433",
  "link": "https://www.microsoft.com/microsoft-365/roadmap?id=141433",
  "category": [
    "Desktop",
    "General Availability",
    "In development",
    "Microsoft 365 app",
    "Worldwide (Standard Multi-Tenant)"
  ],
  "title": "Microsoft 365 app: Loop generates a workspace after your Teams meeting",
  "description": "A workspace is jumpstarted and actively updated as new materials are shared in Teams to enable ongoing collaboration within Loop.",
  "pubDate": "Fri, 31 May 2024 22:30:03 Z",
  "updated": "2024-05-31T22:30:03Z",
  "publicDisclosureAvailabilityDate": "June CY2024",
  "publicPreviewDate": null
}
