{
  "guid": "179897",
  "link": "https://www.microsoft.com/microsoft-365/roadmap?featureid=179897",
  "category": [
    "Desktop",
    "General Availability",
    "Microsoft Teams",
    "Rolling out",
    "Worldwide (Standard Multi-Tenant)"
  ],
  "title": "Microsoft Teams: Enhanced Third Party app purchase experience in Teams and Teams Admin Center",
  "description": "<div><span style=\"font-size:9.0pt;font-family:&quot;Segoe UI&quot;,sans-serif;color:black;\">Shipping\nan enhanced purchase experience in a Teams look and feel for Teams 3 party\napplication in both Teams store and Teams Admin Center. This feature will\nslowly roll out, first to customers with a commerce billing account then to\ncustomer without a commerce billing account.</span> </div>",
  "pubDate": "Thu, 19 Oct 2023 23:13:33 Z",
  "updated": "2024-06-18T23:15:54Z",
  "publicDisclosureAvailabilityDate": "June CY2024",
  "publicPreviewDate": null
}
