{
  "guid": "85644",
  "link": "https://www.microsoft.com/microsoft-365/roadmap?featureid=85644",
  "category": [
    "GCC",
    "GCC High",
    "General Availability",
    "Launched",
    "Microsoft Stream",
    "OneDrive",
    "SharePoint",
    "Web"
  ],
  "title": "Microsoft Stream: Generate captions for a video uploaded to SharePoint and OneDrive for GCC and GCC High",
  "description": "Users with edit permissions to a video file uploaded to SharePoint and OneDrive can click a button in the player to generate closed captions in English.",
  "pubDate": "Mon, 27 Sep 2021 23:08:54 -0700",
  "updated": "2022-06-30T22:01:08-07:00",
  "publicDisclosureAvailabilityDate": "June CY2022",
  "publicPreviewDate": null
}
