{
  "guid": "98193",
  "link": "https://www.microsoft.com/microsoft-365/roadmap?featureid=98193",
  "category": [
    "GCC",
    "General Availability",
    "In development",
    "Microsoft 365 Admin Center",
    "Microsoft Graph",
    "Microsoft Search"
  ],
  "title": "Microsoft Graph: Connectors in GCC",
  "description": "Microsoft Graph Connectors that allow to index third-party content into Microsoft Graph to enable intelligent experiences like Microsoft Search will be available in Government Community Cloud (GCC). GCC-H and DoD launch is coming soon.",
  "pubDate": "Thu, 15 Sep 2022 23:41:58 -0700",
  "updated": "2022-09-15T23:36:46-07:00",
  "publicDisclosureAvailabilityDate": "September CY2022",
  "publicPreviewDate": null
}
