{
  "timestamp": "2024-05-22T02:12:57.1554943+00:00",
  "guid": "388494",
  "link": "https://www.microsoft.com/microsoft-365/roadmap?featureid=388494",
  "category": [
    "GCC",
    "GCC High",
    "General Availability",
    "Microsoft Teams",
    "Rolling out",
    "Teams and Surface Devices",
    "Worldwide (Standard Multi-Tenant)"
  ],
  "title": "Microsoft Teams: Advanced calling and contact management support on non-touch phones",
  "description": "On non-touch phones users can use advanced calling features such as park/unpark calls, busy on busy, auto restart, and manage contacts and contact groups.",
  "pubDate": "Fri, 15 Mar 2024 23:00:39 -0700",
  "updated": "2024-05-22T06:15:05+00:00",
  "publicDisclosureAvailabilityDate": "May CY2024",
  "publicPreviewDate": null
}
