{
  "timestamp": "2023-03-02T06:18:27.0000000+00:00",
  "category": {
    "oldValue": null,
    "newValue": [
      "Cancelled",
      "DoD",
      "GCC",
      "GCC High",
      "General Availability",
      "OneDrive",
      "Targeted Release",
      "Web",
      "Worldwide (Standard Multi-Tenant)"
    ]
  },
  "title": {
    "oldValue": null,
    "newValue": "OneDrive: Sharing experience  - Share menu dropdown"
  },
  "description": {
    "oldValue": null,
    "newValue": "[This item is being postponed indefinitely.] We’re updating the Share menu to provide easy access to additional sharing options like Email, Copy link, Teams chat as well as Manage access settings. <br>GA date: October CY2022"
  }
}
