{
  "timestamp": "2023-03-09T21:11:53.0000000+00:00",
  "description": {
    "oldValue": "Retention policies for Microsoft Teams are being extended to include CDR messages (system-generated messages from Teams meetings). Up until now, only messages generated after October 2022 were supported for retention. This update extends coverage to messages created before October 2022, so that old and new are now supported in the same manner. <br>GA date: June CY2023",
    "newValue": "Retention policies for Microsoft Teams are being extended to include CDR messages (system-generated messages from Teams meetings). Up until now, only messages generated after October 2022 were supported for retention. This update extends coverage to messages created before October 2022, so that old and new are now supported in the same manner."
  },
  "publicDisclosureAvailabilityDate": {
    "oldValue": null,
    "newValue": "June CY2023"
  }
}
